gpt_blazing/__init__.py
gpt_blazing/engine.py
gpt_blazing/engine_pool.py
gpt_blazing/model/__init__.py
gpt_blazing/model/interface.py
gpt_blazing/model/baichuan2/__init__.py
gpt_blazing/model/baichuan2/inference.py
gpt_blazing/model/baichuan2/model.py
gpt_blazing/model/baichuan2/tokenizer.py
gpt_blazing/model/baichuan2/utility.py
gpt_blazing-23.1.0.dev8.dist-info/LICENSE
gpt_blazing-23.1.0.dev8.dist-info/METADATA
gpt_blazing-23.1.0.dev8.dist-info/WHEEL
gpt_blazing-23.1.0.dev8.dist-info/top_level.txt
gpt_blazing-23.1.0.dev8.dist-info/RECORD
