Metadata-Version: 2.1
Name: gpt-blazing
Version: 23.1.0.dev8
Summary: todo
Home-page: https://github.com/huntzhan/gpt-blazing
Author: Hunt Zhan
Author-email: huntzhan.dev@gmail.com
License: Not open source
Requires-Python: <3.12,>=3.8.0
License-File: LICENSE
Requires-Dist: attrs >=22.2.0
Requires-Dist: cattrs >=22.2.0
Requires-Dist: fireball >=0.5.0
Requires-Dist: iolite >=22.1.0
Requires-Dist: torch ==2.2.0.dev20231207
Requires-Dist: numpy >=1.24.4
Requires-Dist: sentencepiece >=0.1.99
Provides-Extra: baichuan2-experiment
Requires-Dist: transformers ==4.33.3 ; extra == 'baichuan2-experiment'
Requires-Dist: accelerate ==0.24.1 ; extra == 'baichuan2-experiment'
Provides-Extra: dev
Requires-Dist: build >=0.2.1 ; extra == 'dev'
Requires-Dist: pytest <7.2.0,>=6.1.2 ; extra == 'dev'
Requires-Dist: pytest-parallel >=0.1.1 ; extra == 'dev'
Requires-Dist: pytest-env >=0.8.1 ; extra == 'dev'
Requires-Dist: yapf >=0.30.0 ; extra == 'dev'
Requires-Dist: flake8 >=3.8.4 ; extra == 'dev'
Requires-Dist: twine >=3.2.0 ; extra == 'dev'
Requires-Dist: ipython >=7.20.0 ; extra == 'dev'
Requires-Dist: pdbpp >=0.10.2 ; extra == 'dev'
Requires-Dist: pdoc >=12.2.0 ; extra == 'dev'
